codenerix_transports/__init__.py
codenerix_transports/admin.py
codenerix_transports/apps.py
codenerix_transports/models.py
codenerix_transports/migrations/0001_initial.py
codenerix_transports/migrations/0002_auto_20171122_1315.py
codenerix_transports/migrations/__init__.py
codenerix_transports/migrations/__pycache__/0001_initial.cpython-35.pyc
codenerix_transports/migrations/__pycache__/0001_initial.cpython-39.pyc
codenerix_transports/migrations/__pycache__/0002_auto_20171122_1315.cpython-35.pyc
codenerix_transports/migrations/__pycache__/0002_auto_20171122_1315.cpython-39.pyc
codenerix_transports/migrations/__pycache__/__init__.cpython-35.pyc
codenerix_transports/migrations/__pycache__/__init__.cpython-39.pyc
django_codenerix_transports-4.0.2.dist-info/LICENSE
django_codenerix_transports-4.0.2.dist-info/METADATA
django_codenerix_transports-4.0.2.dist-info/WHEEL
django_codenerix_transports-4.0.2.dist-info/top_level.txt
django_codenerix_transports-4.0.2.dist-info/RECORD
