Metadata-Version: 2.1
Name: django-codenerix-transports
Version: 4.0.2
Summary: Codenerix Transports is a module that enables CODENERIX to manage transports and let clients to request transport of packages with kwnown companies.
Home-page: https://github.com/codenerix/django-codenerix-transports
Author: Juan Miguel Taboada Godoy <juanmi@juanmitaboada.com>, Juan Soler Ruiz <soleronline@gmail.com>
Author-email: UNKNOWN
License: Apache License Version 2.0
Keywords: django,codenerix,management,erp,crm,transports
Platform: OS Independent
Classifier: Environment :: Web Environment
Classifier: Framework :: Django
Classifier: Framework :: Django :: 1.8
Classifier: Framework :: Django :: 1.9
Classifier: Framework :: Django :: 1.10
Classifier: Intended Audience :: Developers
Classifier: License :: Other/Proprietary License
Classifier: Operating System :: OS Independent
Classifier: Programming Language :: Python
Classifier: Programming Language :: Python :: 2
Classifier: Programming Language :: Python :: 2.7
Classifier: Programming Language :: Python :: 3
Classifier: Programming Language :: Python :: 3.4
Classifier: Programming Language :: Python :: 3.5
Classifier: Topic :: Internet :: WWW/HTTP
Classifier: Topic :: Internet :: WWW/HTTP :: Dynamic Content
Requires-Dist: django-codenerix
Requires-Dist: django-countries
Requires-Dist: suds-community
